LICENSE
README.md
setup.py
./dalab/__init__.py
./dalab/dart.py
./dalab/utils.py
./dalab/visual.py
dalab/__init__.py
dalab/dart.py
dalab/utils.py
dalab/visual.py
dalab.egg-info/PKG-INFO
dalab.egg-info/SOURCES.txt
dalab.egg-info/dependency_links.txt
dalab.egg-info/not-zip-safe
dalab.egg-info/requires.txt
dalab.egg-info/top_level.txt